crossref_commons/__init__.py
crossref_commons/authorization.py
crossref_commons/config.py
crossref_commons/http_utils.py
crossref_commons/iteration.py
crossref_commons/relations.py
crossref_commons/retrieval.py
crossref_commons/sampling.py
crossref_commons/search.py
crossref_commons/types.py
crossref_commons/utils.py
tests/__init__.py
tests/tests_authorization.py
tests/tests_http_utils.py
tests/tests_sampling.py
tests/tests_utils.py
tests_integration/__init__.py
tests_integration/tests_http_utils.py
tests_integration/tests_iteration.py
tests_integration/tests_relations.py
tests_integration/tests_retrieval.py
tests_integration/tests_sampling.py
crossref_commons_reverse-0.0.7.1.dist-info/LICENSE
crossref_commons_reverse-0.0.7.1.dist-info/METADATA
crossref_commons_reverse-0.0.7.1.dist-info/WHEEL
crossref_commons_reverse-0.0.7.1.dist-info/top_level.txt
crossref_commons_reverse-0.0.7.1.dist-info/RECORD
