Metadata-Version: 2.1
Name: crossref-commons-reverse
Version: 0.0.7.1
Summary: Crossref Commons with added Reverse-Search
Home-page: https://gitlab.com/tinloaf/crossref_commons_py
Author: Lukas Barth
Author-email: pypi@mbox.tinloaf.de
License: UNKNOWN
Platform: UNKNOWN
Classifier: Programming Language :: Python :: 3
Classifier: License :: OSI Approved :: MIT License
Classifier: Operating System :: OS Independent
Requires-Dist: ratelimit (>=2.2.1)
Requires-Dist: requests (>=2.18.4)
